sharpe/VERSION.txt
sharpe/__init__.py
sharpe-0.0.1.dist-info/METADATA
sharpe-0.0.1.dist-info/WHEEL
sharpe-0.0.1.dist-info/top_level.txt
sharpe-0.0.1.dist-info/RECORD
